pydantic_graph/__init__.py
pydantic_graph/_utils.py
pydantic_graph/exceptions.py
pydantic_graph/graph.py
pydantic_graph/mermaid.py
pydantic_graph/nodes.py
pydantic_graph/py.typed
pydantic_graph/beta/__init__.py
pydantic_graph/beta/decision.py
pydantic_graph/beta/graph.py
pydantic_graph/beta/graph_builder.py
pydantic_graph/beta/id_types.py
pydantic_graph/beta/join.py
pydantic_graph/beta/mermaid.py
pydantic_graph/beta/node.py
pydantic_graph/beta/node_types.py
pydantic_graph/beta/parent_forks.py
pydantic_graph/beta/paths.py
pydantic_graph/beta/step.py
pydantic_graph/beta/util.py
pydantic_graph/persistence/__init__.py
pydantic_graph/persistence/_utils.py
pydantic_graph/persistence/file.py
pydantic_graph/persistence/in_mem.py
pydantic_graph-1.50.0.dist-info/METADATA
pydantic_graph-1.50.0.dist-info/WHEEL
pydantic_graph-1.50.0.dist-info/licenses/LICENSE
pydantic_graph-1.50.0.dist-info/RECORD
