Metadata-Version: 2.4
Name: pydantic-graph
Version: 1.50.0
Summary: Graph and state machine library
Project-URL: Homepage, https://ai.pydantic.dev/graph/tree/main/pydantic_graph
Project-URL: Source, https://github.com/pydantic/pydantic-ai
Project-URL: Documentation, https://ai.pydantic.dev/graph
Project-URL: Changelog, https://github.com/pydantic/pydantic-ai/releases
Author-email: Samuel Colvin <samuel@pydantic.dev>, Marcelo Trylesinski <marcelotryle@gmail.com>, David Montague <david@pydantic.dev>, Alex Hall <alex@pydantic.dev>, Douwe Maan <douwe@pydantic.dev>
License-Expression: MIT
License-File: LICENSE
Classifier: Development Status :: 5 - Production/Stable
Classifier: Environment :: Console
Classifier: Environment :: MacOS X
Classifier: Intended Audience :: Developers
Classifier: Intended Audience :: Information Technology
Classifier: Intended Audience :: System Administrators
Classifier: License :: OSI Approved :: MIT License
Classifier: Operating System :: POSIX :: Linux
Classifier: Operating System :: Unix
Classifier: Programming Language :: Python
Classifier: Programming Language :: Python :: 3
Classifier: Programming Language :: Python :: 3 :: Only
Classifier: Programming Language :: Python :: 3.10
Classifier: Programming Language :: Python :: 3.11
Classifier: Programming Language :: Python :: 3.12
Classifier: Programming Language :: Python :: 3.13
Classifier: Topic :: Internet
Classifier: Topic :: Software Development :: Libraries :: Python Modules
Requires-Python: >=3.10
Requires-Dist: httpx>=0.27
Requires-Dist: logfire-api>=3.14.1
Requires-Dist: pydantic>=2.10
Requires-Dist: typing-inspection>=0.4.0
